{"id":"F623F18D-986F-48DF-9C35-D34491868731","validationEntity":{"analysedDataType":"auto","dataResult":{"createdDate":"2023-04-25T08:43:08Z"}},"modelEntity":{"createdDate":"2023-04-25T08:43:08Z","id":"507338AE-EE6C-4C90-8F67-49F28658F849","experimentID":"F623F18D-986F-48DF-9C35-D34491868731","title":"","modifiedDate":"2023-04-25T08:43:08Z","preferredFilename":"","version":"1.0","modelURL":"Models\/DogsCatsTransferLearningClassifier%201.mlmodel"},"version":"1.0","settingEntity":{"taskType":"imageClassifier","augmentations":["blur","rotate","addNoise","crop","flip","expose"],"styleTransferAlgorithmType":"image","iterationCount":25,"transferLearningEmbeddingType":"dynamic","harVideoAugmentations":0,"handPoseClassifierAugmentations":[],"algorithmType":"maxEnt","handActionClassifierAugmentations":[],"seedType":"default","featureNames":[]},"state":"trained","trainingEntity":{"finishTime":"2023-04-25T09:31:10Z","validationResults":{"imageClassifier":{"confusionMatrix":[{"expected":"cat","actual":"cat","count":616},{"expected":"dog","actual":"cat","count":342},{"expected":"cat","actual":"dog","count":343},{"expected":"dog","actual":"dog","count":617}],"statsByLabel":{"cat":{"count":958,"precisionRecall":{"success":{"recall":0.64300626304801667,"precision":0.64233576642335766}}},"dog":{"count":960,"precisionRecall":{"success":{"recall":0.64270833333333333,"precision":0.64337851929092804}}}},"accuracy":0.6428571428571429}},"dataURL":"file:\/\/\/Users\/devopsthinh\/Downloads\/CH06code\/datasets\/dogs-vs-cats\/train\/","dataResult":{"itemsCount":202,"createdDate":"2023-04-25T08:43:08Z","dataURL":"file:\/\/\/Users\/devopsthinh\/Downloads\/CH06code\/datasets\/dogs-vs-cats\/train\/","dataSourceID":"42C3055C-61D3-4857-AFFB-295F8CA4D028","classesCount":2,"dataAnalysis":{"summary":{"canUseValidation":1,"classCount":2,"sampleCount":202},"issues":[{"description":"2 classes found, including cat, dog","severity":"debug"},{"description":"202 images found, automatically creating validation set","severity":"good"},{"description":"Smallest class is \"dog\" with 101 images","severity":"debug"},{"description":"Largest class is \"cat\" with 101 images","severity":"debug"}],"classifierAnalysis":{"labelStats":{"cat":101,"dog":101}}}},"trainingResults":{"imageClassifier":{"confusionMatrix":[{"expected":"cat","actual":"cat","count":12576},{"expected":"dog","actual":"cat","count":5959},{"expected":"cat","actual":"dog","count":6409},{"expected":"dog","actual":"dog","count":12124}],"statsByLabel":{"cat":{"count":18535,"precisionRecall":{"success":{"recall":0.67850013487995686,"precision":0.66241769818277585}}},"dog":{"count":18533,"precisionRecall":{"success":{"recall":0.65418442777747798,"precision":0.67046397168611405}}}},"accuracy":0.66634293730441352}},"progress":[{"currentRowIndex":0,"tableIndex":0,"count":0,"isLast":false,"percentComplete":0,"tableDone":false},{"icTrainingColumnHeader":{"hasValidation":true,"elapsedTime":2.9292630000000002,"trainingAccuracy":0.57170600000000005,"iterationCount":1,"validationAccuracy":0.56412899999999999},"isLast":false,"currentRowIndex":0,"count":1,"tableDone":false,"tableIndex":41,"percentComplete":0},{"icTrainingColumnHeader":{"hasValidation":true,"elapsedTime":4.4132530000000001,"trainingAccuracy":0.59293700000000005,"iterationCount":2,"validationAccuracy":0.58967700000000001},"isLast":false,"currentRowIndex":0,"count":2,"tableDone":false,"tableIndex":41,"percentComplete":0},{"icTrainingColumnHeader":{"hasValidation":true,"elapsedTime":7.6258340000000002,"trainingAccuracy":0.59450199999999997,"iterationCount":3,"validationAccuracy":0.59228400000000003},"isLast":false,"currentRowIndex":0,"count":3,"tableDone":false,"tableIndex":41,"percentComplete":0},{"icTrainingColumnHeader":{"hasValidation":true,"elapsedTime":9.0652830000000009,"trainingAccuracy":0.61721700000000002,"iterationCount":4,"validationAccuracy":0.61313899999999999},"isLast":false,"currentRowIndex":0,"count":4,"tableDone":false,"tableIndex":41,"percentComplete":0},{"icTrainingColumnHeader":{"hasValidation":true,"elapsedTime":10.038584,"trainingAccuracy":0.61818799999999996,"iterationCount":5,"validationAccuracy":0.61365999999999998},"isLast":false,"currentRowIndex":0,"count":5,"tableDone":false,"tableIndex":41,"percentComplete":0},{"icTrainingColumnHeader":{"hasValidation":true,"elapsedTime":14.957265,"trainingAccuracy":0.632324,"iterationCount":10,"validationAccuracy":0.63295100000000004},"isLast":false,"currentRowIndex":0,"count":10,"tableDone":false,"tableIndex":41,"percentComplete":0},{"icTrainingColumnHeader":{"hasValidation":true,"elapsedTime":21.606593,"trainingAccuracy":0.65717099999999995,"iterationCount":15,"validationAccuracy":0.63764299999999996},"isLast":false,"currentRowIndex":0,"count":15,"tableDone":false,"tableIndex":41,"percentComplete":0},{"icTrainingColumnHeader":{"hasValidation":true,"elapsedTime":28.237300000000001,"trainingAccuracy":0.66200000000000003,"iterationCount":20,"validationAccuracy":0.64337900000000003},"isLast":false,"currentRowIndex":0,"count":20,"tableDone":false,"tableIndex":41,"percentComplete":0},{"icTrainingColumnHeader":{"hasValidation":true,"elapsedTime":33.081681000000003,"trainingAccuracy":0.66634300000000002,"iterationCount":25,"validationAccuracy":0.64285700000000001},"isLast":false,"currentRowIndex":0,"count":25,"tableDone":true,"tableIndex":41,"percentComplete":0},{"currentRowIndex":0,"tableIndex":0,"count":30,"isLast":false,"percentComplete":0,"tableDone":false},{"currentRowIndex":0,"tableIndex":0,"count":35,"isLast":false,"percentComplete":0,"tableDone":false},{"currentRowIndex":0,"tableIndex":0,"count":40,"isLast":false,"percentComplete":0,"tableDone":false},{"currentRowIndex":0,"tableIndex":0,"count":45,"isLast":false,"percentComplete":0,"tableDone":false},{"currentRowIndex":0,"tableIndex":0,"count":50,"isLast":false,"percentComplete":0,"tableDone":false},{"currentRowIndex":0,"tableIndex":0,"count":55,"isLast":false,"percentComplete":0,"tableDone":false},{"currentRowIndex":0,"tableIndex":0,"count":60,"isLast":false,"percentComplete":0,"tableDone":false},{"currentRowIndex":0,"tableIndex":0,"count":65,"isLast":false,"percentComplete":0,"tableDone":false},{"currentRowIndex":0,"tableIndex":0,"count":70,"isLast":false,"percentComplete":0,"tableDone":false},{"currentRowIndex":0,"tableIndex":0,"count":75,"isLast":false,"percentComplete":0,"tableDone":false},{"currentRowIndex":0,"tableIndex":0,"count":80,"isLast":false,"percentComplete":0,"tableDone":false},{"currentRowIndex":0,"tableIndex":0,"count":85,"isLast":false,"percentComplete":0,"tableDone":false},{"currentRowIndex":0,"tableIndex":0,"count":90,"isLast":false,"percentComplete":0,"tableDone":false},{"currentRowIndex":0,"tableIndex":0,"count":95,"isLast":false,"percentComplete":0,"tableDone":false},{"currentRowIndex":0,"tableIndex":0,"count":100,"isLast":false,"percentComplete":0,"tableDone":false},{"currentRowIndex":0,"tableIndex":0,"count":105,"isLast":false,"percentComplete":0,"tableDone":false},{"currentRowIndex":0,"tableIndex":0,"count":110,"isLast":false,"percentComplete":0,"tableDone":false},{"currentRowIndex":0,"tableIndex":0,"count":115,"isLast":false,"percentComplete":0,"tableDone":false},{"currentRowIndex":0,"tableIndex":0,"count":120,"isLast":false,"percentComplete":0,"tableDone":false},{"currentRowIndex":0,"tableIndex":0,"count":125,"isLast":false,"percentComplete":0,"tableDone":false},{"currentRowIndex":0,"tableIndex":0,"count":130,"isLast":false,"percentComplete":0,"tableDone":false},{"currentRowIndex":0,"tableIndex":0,"count":135,"isLast":false,"percentComplete":0,"tableDone":false},{"currentRowIndex":0,"tableIndex":0,"count":140,"isLast":false,"percentComplete":0,"tableDone":false},{"currentRowIndex":0,"tableIndex":0,"count":145,"isLast":false,"percentComplete":0,"tableDone":false},{"currentRowIndex":0,"tableIndex":0,"count":150,"isLast":false,"percentComplete":0,"tableDone":false},{"currentRowIndex":0,"tableIndex":0,"count":155,"isLast":false,"percentComplete":0,"tableDone":false},{"currentRowIndex":0,"tableIndex":0,"count":160,"isLast":false,"percentComplete":0,"tableDone":false},{"currentRowIndex":0,"tableIndex":0,"count":165,"isLast":false,"percentComplete":0,"tableDone":false},{"currentRowIndex":0,"tableIndex":0,"count":170,"isLast":false,"percentComplete":0,"tableDone":false},{"currentRowIndex":0,"tableIndex":0,"count":175,"isLast":false,"percentComplete":0,"tableDone":false},{"currentRowIndex":0,"tableIndex":0,"count":180,"isLast":false,"percentComplete":0,"tableDone":false},{"currentRowIndex":0,"tableIndex":0,"count":185,"isLast":false,"percentComplete":0,"tableDone":false},{"currentRowIndex":0,"tableIndex":0,"count":190,"isLast":false,"percentComplete":0,"tableDone":false},{"currentRowIndex":0,"tableIndex":0,"count":195,"isLast":false,"percentComplete":0,"tableDone":false},{"currentRowIndex":0,"tableIndex":0,"count":200,"isLast":false,"percentComplete":0,"tableDone":false},{"currentRowIndex":0,"tableIndex":0,"count":202,"isLast":false,"percentComplete":0,"tableDone":true}],"trainingAccuracy":0.66634293730441352,"checkpointMetrics":{},"analysedDataType":"datasource","dataSourceID":"42C3055C-61D3-4857-AFFB-295F8CA4D028","snapshottableCheckpoints":{},"featureExtractionCheckpointMayBeAvailable":false,"validationAccuracy":0.6428571428571429,"startTime":"2023-04-25T08:54:03Z"},"createdDate":"2023-04-25T08:43:08Z","evaluationContainerEntity":{"testingEvaluationEntity":{"id":"7a5e3749-ed65-4860-84d1-ae55ad264681","createdDate":"2023-04-25T08:43:08Z","dataResult":{"createdDate":"2023-04-25T08:43:08Z"},"analysedDataType":"none"},"createdDate":"2023-04-25T11:12:28Z","id":"191090da-19db-4a94-9cb4-505faed028a7","trainingEvaluationEntity":{"evaluationResult":{"imageClassifier":{"confusionMatrix":[{"expected":"cat","actual":"cat","count":12576},{"expected":"dog","actual":"cat","count":5959},{"expected":"cat","actual":"dog","count":6409},{"expected":"dog","actual":"dog","count":12124}],"statsByLabel":{"cat":{"count":18535,"precisionRecall":{"success":{"recall":0.67850013487995686,"precision":0.66241769818277585}}},"dog":{"count":18533,"precisionRecall":{"success":{"recall":0.65418442777747798,"precision":0.67046397168611405}}}},"accuracy":0.66634293730441352}},"createdDate":"2023-04-25T08:43:08Z","id":"75131cf0-98e2-49ae-b7b4-71dfbfa61fd4","dataURL":"file:\/\/\/Users\/devopsthinh\/Downloads\/CH06code\/datasets\/dogs-vs-cats\/train\/","dataSourceID":"42C3055C-61D3-4857-AFFB-295F8CA4D028","dataResult":{"itemsCount":202,"createdDate":"2023-04-25T08:43:08Z","dataURL":"file:\/\/\/Users\/devopsthinh\/Downloads\/CH06code\/datasets\/dogs-vs-cats\/train\/","dataSourceID":"42C3055C-61D3-4857-AFFB-295F8CA4D028","classesCount":2,"dataAnalysis":{"summary":{"canUseValidation":1,"classCount":2,"sampleCount":202},"issues":[{"description":"2 classes found, including cat, dog","severity":"debug"},{"description":"202 images found, automatically creating validation set","severity":"good"},{"description":"Smallest class is \"dog\" with 101 images","severity":"debug"},{"description":"Largest class is \"cat\" with 101 images","severity":"debug"}],"classifierAnalysis":{"labelStats":{"cat":101,"dog":101}}}},"analysedDataType":"none"},"previewType":"imageClassifier","modifiedDate":"2023-04-25T11:12:28Z","validationEvaluationEntity":{"id":"1106be6d-1b89-4614-b5a6-bee54f069f2a","createdDate":"2023-04-25T08:43:08Z","dataResult":{"createdDate":"2023-04-25T08:43:08Z"},"analysedDataType":"auto","evaluationResult":{"imageClassifier":{"confusionMatrix":[{"expected":"cat","actual":"cat","count":616},{"expected":"dog","actual":"cat","count":342},{"expected":"cat","actual":"dog","count":343},{"expected":"dog","actual":"dog","count":617}],"statsByLabel":{"cat":{"count":958,"precisionRecall":{"success":{"recall":0.64300626304801667,"precision":0.64233576642335766}}},"dog":{"count":960,"precisionRecall":{"success":{"recall":0.64270833333333333,"precision":0.64337851929092804}}}},"accuracy":0.6428571428571429}}},"evaluationEntities":[{"evaluationResult":{"imageClassifier":{"confusionMatrix":[{"expected":"cat","actual":"cat","count":99},{"expected":"dog","actual":"cat","count":2},{"expected":"dog","actual":"dog","count":101}],"detail":{"predictions":{"cat":[{"falsePositive":{}},[],{"falseNegative":{}},[{"predictions":{"cat":0.45210838317871094,"dog":0.54789161682128906},"actual":"cat","predicted":"dog","url":"file:\/\/\/Users\/devopsthinh\/Downloads\/CH06code\/datasets\/dogs-vs-cats\/test\/cat\/cat.171.jpg"},{"predictions":{"dog":0.85519981384277344,"cat":0.14480018615722656},"actual":"cat","predicted":"dog","url":"file:\/\/\/Users\/devopsthinh\/Downloads\/CH06code\/datasets\/dogs-vs-cats\/test\/cat\/cat.146.jpg"}],{"truePositive":{}},[{"predictions":{"dog":0.00014776631724089384,"cat":0.99985224008560181},"actual":"cat","predicted":"cat","url":"file:\/\/\/Users\/devopsthinh\/Downloads\/CH06code\/datasets\/dogs-vs-cats\/test\/cat\/cat.198.jpg"},{"predictions":{"dog":0.0017670277738943696,"cat":0.99823296070098877},"actual":"cat","predicted":"cat","url":"file:\/\/\/Users\/devopsthinh\/Downloads\/CH06code\/datasets\/dogs-vs-cats\/test\/cat\/cat.167.jpg"},{"predictions":{"cat":0.99504435062408447,"dog":0.0049556554295122623},"actual":"cat","predicted":"cat","url":"file:\/\/\/Users\/devopsthinh\/Downloads\/CH06code\/datasets\/dogs-vs-cats\/test\/cat\/cat.173.jpg"},{"predictions":{"cat":0.99980270862579346,"dog":0.00019727434846572578},"actual":"cat","predicted":"cat","url":"file:\/\/\/Users\/devopsthinh\/Downloads\/CH06code\/datasets\/dogs-vs-cats\/test\/cat\/cat.172.jpg"},{"predictions":{"cat":0.80729490518569946,"dog":0.19270512461662292},"actual":"cat","predicted":"cat","url":"file:\/\/\/Users\/devopsthinh\/Downloads\/CH06code\/datasets\/dogs-vs-cats\/test\/cat\/cat.166.jpg"},{"predictions":{"dog":0.0021287966519594193,"cat":0.99787122011184692},"actual":"cat","predicted":"cat","url":"file:\/\/\/Users\/devopsthinh\/Downloads\/CH06code\/datasets\/dogs-vs-cats\/test\/cat\/cat.199.jpg"},{"predictions":{"cat":0.99838262796401978,"dog":0.0016173836775124073},"actual":"cat","predicted":"cat","url":"file:\/\/\/Users\/devopsthinh\/Downloads\/CH06code\/datasets\/dogs-vs-cats\/test\/cat\/cat.158.jpg"},{"predictions":{"cat":0.99420285224914551,"dog":0.0057971286587417126},"actual":"cat","predicted":"cat","url":"file:\/\/\/Users\/devopsthinh\/Downloads\/CH06code\/datasets\/dogs-vs-cats\/test\/cat\/cat.170.jpg"},{"predictions":{"dog":0.02850341796875,"cat":0.97149658203125},"actual":"cat","predicted":"cat","url":"file:\/\/\/Users\/devopsthinh\/Downloads\/CH06code\/datasets\/dogs-vs-cats\/test\/cat\/cat.164.jpg"},{"predictions":{"cat":0.99536168575286865,"dog":0.0046383105218410492},"actual":"cat","predicted":"cat","url":"file:\/\/\/Users\/devopsthinh\/Downloads\/CH06code\/datasets\/dogs-vs-cats\/test\/cat\/cat.165.jpg"},{"predictions":{"cat":0.9943196177482605,"dog":0.0056803799234330654},"actual":"cat","predicted":"cat","url":"file:\/\/\/Users\/devopsthinh\/Downloads\/CH06code\/datasets\/dogs-vs-cats\/test\/cat\/cat.159.jpg"},{"predictions":{"cat":0.99980580806732178,"dog":0.00019418341980781406},"actual":"cat","predicted":"cat","url":"file:\/\/\/Users\/devopsthinh\/Downloads\/CH06code\/datasets\/dogs-vs-cats\/test\/cat\/cat.175.jpg"},{"predictions":{"cat":0.97466093301773071,"dog":0.025339068844914436},"actual":"cat","predicted":"cat","url":"file:\/\/\/Users\/devopsthinh\/Downloads\/CH06code\/datasets\/dogs-vs-cats\/test\/cat\/cat.161.jpg"},{"predictions":{"dog":0.0044234395027160645,"cat":0.99557656049728394},"actual":"cat","predicted":"cat","url":"file:\/\/\/Users\/devopsthinh\/Downloads\/CH06code\/datasets\/dogs-vs-cats\/test\/cat\/cat.149.jpg"},{"predictions":{"dog":0.0096886642277240753,"cat":0.99031132459640503},"actual":"cat","predicted":"cat","url":"file:\/\/\/Users\/devopsthinh\/Downloads\/CH06code\/datasets\/dogs-vs-cats\/test\/cat\/cat.148.jpg"},{"predictions":{"cat":0.99960809946060181,"dog":0.00039189413655549288},"actual":"cat","predicted":"cat","url":"file:\/\/\/Users\/devopsthinh\/Downloads\/CH06code\/datasets\/dogs-vs-cats\/test\/cat\/cat.160.jpg"},{"predictions":{"cat":0.99292021989822388,"dog":0.007079793605953455},"actual":"cat","predicted":"cat","url":"file:\/\/\/Users\/devopsthinh\/Downloads\/CH06code\/datasets\/dogs-vs-cats\/test\/cat\/cat.174.jpg"},{"predictions":{"cat":0.9905739426612854,"dog":0.0094260768964886665},"actual":"cat","predicted":"cat","url":"file:\/\/\/Users\/devopsthinh\/Downloads\/CH06code\/datasets\/dogs-vs-cats\/test\/cat\/cat.200.jpg"},{"predictions":{"dog":0.0070819244720041752,"cat":0.99291807413101196},"actual":"cat","predicted":"cat","url":"file:\/\/\/Users\/devopsthinh\/Downloads\/CH06code\/datasets\/dogs-vs-cats\/test\/cat\/cat.189.jpg"},{"predictions":{"dog":0.0083725545555353165,"cat":0.99162745475769043},"actual":"cat","predicted":"cat","url":"file:\/\/\/Users\/devopsthinh\/Downloads\/CH06code\/datasets\/dogs-vs-cats\/test\/cat\/cat.162.jpg"},{"predictions":{"cat":0.99780118465423584,"dog":0.00219882489182055},"actual":"cat","predicted":"cat","url":"file:\/\/\/Users\/devopsthinh\/Downloads\/CH06code\/datasets\/dogs-vs-cats\/test\/cat\/cat.176.jpg"},{"predictions":{"dog":0.015432878397405148,"cat":0.98456710577011108},"actual":"cat","predicted":"cat","url":"file:\/\/\/Users\/devopsthinh\/Downloads\/CH06code\/datasets\/dogs-vs-cats\/test\/cat\/cat.177.jpg"},{"predictions":{"cat":0.99605607986450195,"dog":0.0039439299143850803},"actual":"cat","predicted":"cat","url":"file:\/\/\/Users\/devopsthinh\/Downloads\/CH06code\/datasets\/dogs-vs-cats\/test\/cat\/cat.163.jpg"},{"predictions":{"cat":0.99564617872238159,"dog":0.0043537924066185951},"actual":"cat","predicted":"cat","url":"file:\/\/\/Users\/devopsthinh\/Downloads\/CH06code\/datasets\/dogs-vs-cats\/test\/cat\/cat.188.jpg"},{"predictions":{"cat":0.99027234315872192,"dog":0.0097276642918586731},"actual":"cat","predicted":"cat","url":"file:\/\/\/Users\/devopsthinh\/Downloads\/CH06code\/datasets\/dogs-vs-cats\/test\/cat\/cat.201.jpg"},{"predictions":{"cat":0.99815171957015991,"dog":0.0018482679734006524},"actual":"cat","predicted":"cat","url":"file:\/\/\/Users\/devopsthinh\/Downloads\/CH06code\/datasets\/dogs-vs-cats\/test\/cat\/cat.138.jpg"},{"predictions":{"cat":0.99242210388183594,"dog":0.007577918004244566},"actual":"cat","predicted":"cat","url":"file:\/\/\/Users\/devopsthinh\/Downloads\/CH06code\/datasets\/dogs-vs-cats\/test\/cat\/cat.104.jpg"},{"predictions":{"cat":0.9979282021522522,"dog":0.0020717931911349297},"actual":"cat","predicted":"cat","url":"file:\/\/\/Users\/devopsthinh\/Downloads\/CH06code\/datasets\/dogs-vs-cats\/test\/cat\/cat.110.jpg"},{"predictions":{"dog":0.0019265944138169289,"cat":0.99807339906692505},"actual":"cat","predicted":"cat","url":"file:\/\/\/Users\/devopsthinh\/Downloads\/CH06code\/datasets\/dogs-vs-cats\/test\/cat\/cat.111.jpg"},{"predictions":{"cat":0.98641854524612427,"dog":0.013581424951553345},"actual":"cat","predicted":"cat","url":"file:\/\/\/Users\/devopsthinh\/Downloads\/CH06code\/datasets\/dogs-vs-cats\/test\/cat\/cat.105.jpg"},{"predictions":{"dog":0.062855638563632965,"cat":0.93714433908462524},"actual":"cat","predicted":"cat","url":"file:\/\/\/Users\/devopsthinh\/Downloads\/CH06code\/datasets\/dogs-vs-cats\/test\/cat\/cat.139.jpg"},{"predictions":{"dog":0.041691828519105911,"cat":0.95830816030502319},"actual":"cat","predicted":"cat","url":"file:\/\/\/Users\/devopsthinh\/Downloads\/CH06code\/datasets\/dogs-vs-cats\/test\/cat\/cat.113.jpg"},{"predictions":{"cat":0.99777746200561523,"dog":0.0022225501015782356},"actual":"cat","predicted":"cat","url":"file:\/\/\/Users\/devopsthinh\/Downloads\/CH06code\/datasets\/dogs-vs-cats\/test\/cat\/cat.107.jpg"},{"predictions":{"cat":0.99803268909454346,"dog":0.0019672873895615339},"actual":"cat","predicted":"cat","url":"file:\/\/\/Users\/devopsthinh\/Downloads\/CH06code\/datasets\/dogs-vs-cats\/test\/cat\/cat.106.jpg"},{"predictions":{"dog":0.15569460391998291,"cat":0.84430539608001709},"actual":"cat","predicted":"cat","url":"file:\/\/\/Users\/devopsthinh\/Downloads\/CH06code\/datasets\/dogs-vs-cats\/test\/cat\/cat.112.jpg"},{"predictions":{"cat":0.99640077352523804,"dog":0.0035992078483104706},"actual":"cat","predicted":"cat","url":"file:\/\/\/Users\/devopsthinh\/Downloads\/CH06code\/datasets\/dogs-vs-cats\/test\/cat\/cat.116.jpg"},{"predictions":{"cat":0.9994385838508606,"dog":0.00056138832587748766},"actual":"cat","predicted":"cat","url":"file:\/\/\/Users\/devopsthinh\/Downloads\/CH06code\/datasets\/dogs-vs-cats\/test\/cat\/cat.102.jpg"},{"predictions":{"dog":0.00014570482017006725,"cat":0.99985426664352417},"actual":"cat","predicted":"cat","url":"file:\/\/\/Users\/devopsthinh\/Downloads\/CH06code\/datasets\/dogs-vs-cats\/test\/cat\/cat.103.jpg"},{"predictions":{"dog":0.00375757971778512,"cat":0.99624240398406982},"actual":"cat","predicted":"cat","url":"file:\/\/\/Users\/devopsthinh\/Downloads\/CH06code\/datasets\/dogs-vs-cats\/test\/cat\/cat.117.jpg"},{"predictions":{"cat":0.78569662570953369,"dog":0.21430335938930511},"actual":"cat","predicted":"cat","url":"file:\/\/\/Users\/devopsthinh\/Downloads\/CH06code\/datasets\/dogs-vs-cats\/test\/cat\/cat.101.jpg"},{"predictions":{"dog":0.01296495646238327,"cat":0.98703503608703613},"actual":"cat","predicted":"cat","url":"file:\/\/\/Users\/devopsthinh\/Downloads\/CH06code\/datasets\/dogs-vs-cats\/test\/cat\/cat.115.jpg"},{"predictions":{"dog":0.033864200115203857,"cat":0.96613579988479614},"actual":"cat","predicted":"cat","url":"file:\/\/\/Users\/devopsthinh\/Downloads\/CH06code\/datasets\/dogs-vs-cats\/test\/cat\/cat.129.jpg"},{"predictions":{"dog":0.0033303769305348396,"cat":0.99666965007781982},"actual":"cat","predicted":"cat","url":"file:\/\/\/Users\/devopsthinh\/Downloads\/CH06code\/datasets\/dogs-vs-cats\/test\/cat\/cat.128.jpg"},{"predictions":{"cat":0.67870569229125977,"dog":0.32129433751106262},"actual":"cat","predicted":"cat","url":"file:\/\/\/Users\/devopsthinh\/Downloads\/CH06code\/datasets\/dogs-vs-cats\/test\/cat\/cat.114.jpg"},{"predictions":{"dog":0.018258022144436836,"cat":0.98174196481704712},"actual":"cat","predicted":"cat","url":"file:\/\/\/Users\/devopsthinh\/Downloads\/CH06code\/datasets\/dogs-vs-cats\/test\/cat\/cat.119.jpg"},{"predictions":{"cat":0.95620888471603394,"dog":0.043791115283966064},"actual":"cat","predicted":"cat","url":"file:\/\/\/Users\/devopsthinh\/Downloads\/CH06code\/datasets\/dogs-vs-cats\/test\/cat\/cat.125.jpg"},{"predictions":{"dog":4.2620551539584994e-05,"cat":0.9999573826789856},"actual":"cat","predicted":"cat","url":"file:\/\/\/Users\/devopsthinh\/Downloads\/CH06code\/datasets\/dogs-vs-cats\/test\/cat\/cat.131.jpg"},{"predictions":{"cat":0.99531906843185425,"dog":0.0046809534542262554},"actual":"cat","predicted":"cat","url":"file:\/\/\/Users\/devopsthinh\/Downloads\/CH06code\/datasets\/dogs-vs-cats\/test\/cat\/cat.130.jpg"},{"predictions":{"dog":0.0078640272840857506,"cat":0.99213600158691406},"actual":"cat","predicted":"cat","url":"file:\/\/\/Users\/devopsthinh\/Downloads\/CH06code\/datasets\/dogs-vs-cats\/test\/cat\/cat.124.jpg"},{"predictions":{"cat":0.99426990747451782,"dog":0.0057301046326756477},"actual":"cat","predicted":"cat","url":"file:\/\/\/Users\/devopsthinh\/Downloads\/CH06code\/datasets\/dogs-vs-cats\/test\/cat\/cat.118.jpg"},{"predictions":{"cat":0.99491357803344727,"dog":0.0050864163786172867},"actual":"cat","predicted":"cat","url":"file:\/\/\/Users\/devopsthinh\/Downloads\/CH06code\/datasets\/dogs-vs-cats\/test\/cat\/cat.132.jpg"},{"predictions":{"dog":0.00021637836471199989,"cat":0.99978363513946533},"actual":"cat","predicted":"cat","url":"file:\/\/\/Users\/devopsthinh\/Downloads\/CH06code\/datasets\/dogs-vs-cats\/test\/cat\/cat.126.jpg"},{"predictions":{"cat":0.99421590566635132,"dog":0.005784105509519577},"actual":"cat","predicted":"cat","url":"file:\/\/\/Users\/devopsthinh\/Downloads\/CH06code\/datasets\/dogs-vs-cats\/test\/cat\/cat.127.jpg"},{"predictions":{"cat":0.99866402149200439,"dog":0.0013359836302697659},"actual":"cat","predicted":"cat","url":"file:\/\/\/Users\/devopsthinh\/Downloads\/CH06code\/datasets\/dogs-vs-cats\/test\/cat\/cat.133.jpg"},{"predictions":{"cat":0.87303352355957031,"dog":0.12696646153926849},"actual":"cat","predicted":"cat","url":"file:\/\/\/Users\/devopsthinh\/Downloads\/CH06code\/datasets\/dogs-vs-cats\/test\/cat\/cat.137.jpg"},{"predictions":{"dog":0.057939391583204269,"cat":0.94206058979034424},"actual":"cat","predicted":"cat","url":"file:\/\/\/Users\/devopsthinh\/Downloads\/CH06code\/datasets\/dogs-vs-cats\/test\/cat\/cat.123.jpg"},{"predictions":{"cat":0.99906569719314575,"dog":0.00093429390108212829},"actual":"cat","predicted":"cat","url":"file:\/\/\/Users\/devopsthinh\/Downloads\/CH06code\/datasets\/dogs-vs-cats\/test\/cat\/cat.122.jpg"},{"predictions":{"cat":0.99695801734924316,"dog":0.003041981952264905},"actual":"cat","predicted":"cat","url":"file:\/\/\/Users\/devopsthinh\/Downloads\/CH06code\/datasets\/dogs-vs-cats\/test\/cat\/cat.136.jpg"},{"predictions":{"cat":0.99859529733657837,"dog":0.001404687762260437},"actual":"cat","predicted":"cat","url":"file:\/\/\/Users\/devopsthinh\/Downloads\/CH06code\/datasets\/dogs-vs-cats\/test\/cat\/cat.120.jpg"},{"predictions":{"cat":0.92998743057250977,"dog":0.070012576878070831},"actual":"cat","predicted":"cat","url":"file:\/\/\/Users\/devopsthinh\/Downloads\/CH06code\/datasets\/dogs-vs-cats\/test\/cat\/cat.134.jpg"},{"predictions":{"cat":0.81806504726409912,"dog":0.18193498253822327},"actual":"cat","predicted":"cat","url":"file:\/\/\/Users\/devopsthinh\/Downloads\/CH06code\/datasets\/dogs-vs-cats\/test\/cat\/cat.108.jpg"},{"predictions":{"cat":0.99825042486190796,"dog":0.0017495955107733607},"actual":"cat","predicted":"cat","url":"file:\/\/\/Users\/devopsthinh\/Downloads\/CH06code\/datasets\/dogs-vs-cats\/test\/cat\/cat.109.jpg"},{"predictions":{"dog":0.01790609210729599,"cat":0.9820939302444458},"actual":"cat","predicted":"cat","url":"file:\/\/\/Users\/devopsthinh\/Downloads\/CH06code\/datasets\/dogs-vs-cats\/test\/cat\/cat.135.jpg"},{"predictions":{"dog":0.12945251166820526,"cat":0.87054747343063354},"actual":"cat","predicted":"cat","url":"file:\/\/\/Users\/devopsthinh\/Downloads\/CH06code\/datasets\/dogs-vs-cats\/test\/cat\/cat.121.jpg"},{"predictions":{"cat":0.99030250310897827,"dog":0.0096974875777959824},"actual":"cat","predicted":"cat","url":"file:\/\/\/Users\/devopsthinh\/Downloads\/CH06code\/datasets\/dogs-vs-cats\/test\/cat\/cat.185.jpg"},{"predictions":{"dog":0.0030316542834043503,"cat":0.99696832895278931},"actual":"cat","predicted":"cat","url":"file:\/\/\/Users\/devopsthinh\/Downloads\/CH06code\/datasets\/dogs-vs-cats\/test\/cat\/cat.191.jpg"},{"predictions":{"dog":0.00094976968830451369,"cat":0.99905025959014893},"actual":"cat","predicted":"cat","url":"file:\/\/\/Users\/devopsthinh\/Downloads\/CH06code\/datasets\/dogs-vs-cats\/test\/cat\/cat.152.jpg"},{"predictions":{"dog":0.0075167883187532425,"cat":0.99248319864273071},"actual":"cat","predicted":"cat","url":"file:\/\/\/Users\/devopsthinh\/Downloads\/CH06code\/datasets\/dogs-vs-cats\/test\/cat\/cat.153.jpg"},{"predictions":{"cat":0.97899585962295532,"dog":0.021004151552915573},"actual":"cat","predicted":"cat","url":"file:\/\/\/Users\/devopsthinh\/Downloads\/CH06code\/datasets\/dogs-vs-cats\/test\/cat\/cat.147.jpg"},{"predictions":{"dog":0.0035970259923487902,"cat":0.99640297889709473},"actual":"cat","predicted":"cat","url":"file:\/\/\/Users\/devopsthinh\/Downloads\/CH06code\/datasets\/dogs-vs-cats\/test\/cat\/cat.190.jpg"},{"predictions":{"dog":0.0063333287835121155,"cat":0.99366664886474609},"actual":"cat","predicted":"cat","url":"file:\/\/\/Users\/devopsthinh\/Downloads\/CH06code\/datasets\/dogs-vs-cats\/test\/cat\/cat.184.jpg"},{"predictions":{"dog":0.0017675765557214618,"cat":0.99823242425918579},"actual":"cat","predicted":"cat","url":"file:\/\/\/Users\/devopsthinh\/Downloads\/CH06code\/datasets\/dogs-vs-cats\/test\/cat\/cat.192.jpg"},{"predictions":{"dog":0.0050128484144806862,"cat":0.9949871301651001},"actual":"cat","predicted":"cat","url":"file:\/\/\/Users\/devopsthinh\/Downloads\/CH06code\/datasets\/dogs-vs-cats\/test\/cat\/cat.186.jpg"},{"predictions":{"cat":0.9681592583656311,"dog":0.031840760260820389},"actual":"cat","predicted":"cat","url":"file:\/\/\/Users\/devopsthinh\/Downloads\/CH06code\/datasets\/dogs-vs-cats\/test\/cat\/cat.179.jpg"},{"predictions":{"dog":0.0032546899747103453,"cat":0.99674528837203979},"actual":"cat","predicted":"cat","url":"file:\/\/\/Users\/devopsthinh\/Downloads\/CH06code\/datasets\/dogs-vs-cats\/test\/cat\/cat.151.jpg"},{"predictions":{"dog":0.011254863813519478,"cat":0.98874515295028687},"actual":"cat","predicted":"cat","url":"file:\/\/\/Users\/devopsthinh\/Downloads\/CH06code\/datasets\/dogs-vs-cats\/test\/cat\/cat.145.jpg"},{"predictions":{"cat":0.99738019704818726,"dog":0.0026197836268693209},"actual":"cat","predicted":"cat","url":"file:\/\/\/Users\/devopsthinh\/Downloads\/CH06code\/datasets\/dogs-vs-cats\/test\/cat\/cat.144.jpg"},{"predictions":{"dog":0.0033306649420410395,"cat":0.99666935205459595},"actual":"cat","predicted":"cat","url":"file:\/\/\/Users\/devopsthinh\/Downloads\/CH06code\/datasets\/dogs-vs-cats\/test\/cat\/cat.150.jpg"},{"predictions":{"dog":0.014558497816324234,"cat":0.98544150590896606},"actual":"cat","predicted":"cat","url":"file:\/\/\/Users\/devopsthinh\/Downloads\/CH06code\/datasets\/dogs-vs-cats\/test\/cat\/cat.178.jpg"},{"predictions":{"cat":0.99506211280822754,"dog":0.0049379123374819756},"actual":"cat","predicted":"cat","url":"file:\/\/\/Users\/devopsthinh\/Downloads\/CH06code\/datasets\/dogs-vs-cats\/test\/cat\/cat.187.jpg"},{"predictions":{"dog":0.00020941629190929234,"cat":0.99979060888290405},"actual":"cat","predicted":"cat","url":"file:\/\/\/Users\/devopsthinh\/Downloads\/CH06code\/datasets\/dogs-vs-cats\/test\/cat\/cat.193.jpg"},{"predictions":{"dog":0.073421090841293335,"cat":0.92657887935638428},"actual":"cat","predicted":"cat","url":"file:\/\/\/Users\/devopsthinh\/Downloads\/CH06code\/datasets\/dogs-vs-cats\/test\/cat\/cat.197.jpg"},{"predictions":{"dog":0.017084773629903793,"cat":0.98291522264480591},"actual":"cat","predicted":"cat","url":"file:\/\/\/Users\/devopsthinh\/Downloads\/CH06code\/datasets\/dogs-vs-cats\/test\/cat\/cat.183.jpg"},{"predictions":{"cat":0.99899381399154663,"dog":0.0010061945067718625},"actual":"cat","predicted":"cat","url":"file:\/\/\/Users\/devopsthinh\/Downloads\/CH06code\/datasets\/dogs-vs-cats\/test\/cat\/cat.154.jpg"},{"predictions":{"dog":0.0013560685329139233,"cat":0.99864393472671509},"actual":"cat","predicted":"cat","url":"file:\/\/\/Users\/devopsthinh\/Downloads\/CH06code\/datasets\/dogs-vs-cats\/test\/cat\/cat.140.jpg"},{"predictions":{"dog":0.0039931177161633968,"cat":0.99600690603256226},"actual":"cat","predicted":"cat","url":"file:\/\/\/Users\/devopsthinh\/Downloads\/CH06code\/datasets\/dogs-vs-cats\/test\/cat\/cat.168.jpg"},{"predictions":{"cat":0.92605888843536377,"dog":0.073941119015216827},"actual":"cat","predicted":"cat","url":"file:\/\/\/Users\/devopsthinh\/Downloads\/CH06code\/datasets\/dogs-vs-cats\/test\/cat\/cat.169.jpg"},{"predictions":{"dog":0.021825425326824188,"cat":0.97817456722259521},"actual":"cat","predicted":"cat","url":"file:\/\/\/Users\/devopsthinh\/Downloads\/CH06code\/datasets\/dogs-vs-cats\/test\/cat\/cat.141.jpg"},{"predictions":{"cat":0.94967657327651978,"dog":0.050323434174060822},"actual":"cat","predicted":"cat","url":"file:\/\/\/Users\/devopsthinh\/Downloads\/CH06code\/datasets\/dogs-vs-cats\/test\/cat\/cat.155.jpg"},{"predictions":{"dog":0.0038068222347646952,"cat":0.99619317054748535},"actual":"cat","predicted":"cat","url":"file:\/\/\/Users\/devopsthinh\/Downloads\/CH06code\/datasets\/dogs-vs-cats\/test\/cat\/cat.182.jpg"},{"predictions":{"cat":0.98529207706451416,"dog":0.014707944355905056},"actual":"cat","predicted":"cat","url":"file:\/\/\/Users\/devopsthinh\/Downloads\/CH06code\/datasets\/dogs-vs-cats\/test\/cat\/cat.196.jpg"},{"predictions":{"cat":0.99840360879898071,"dog":0.00159638118930161},"actual":"cat","predicted":"cat","url":"file:\/\/\/Users\/devopsthinh\/Downloads\/CH06code\/datasets\/dogs-vs-cats\/test\/cat\/cat.180.jpg"},{"predictions":{"dog":0.0097663011401891708,"cat":0.99023371934890747},"actual":"cat","predicted":"cat","url":"file:\/\/\/Users\/devopsthinh\/Downloads\/CH06code\/datasets\/dogs-vs-cats\/test\/cat\/cat.194.jpg"},{"predictions":{"cat":0.98544341325759888,"dog":0.014556587673723698},"actual":"cat","predicted":"cat","url":"file:\/\/\/Users\/devopsthinh\/Downloads\/CH06code\/datasets\/dogs-vs-cats\/test\/cat\/cat.143.jpg"},{"predictions":{"dog":6.2049693951848894e-05,"cat":0.99993795156478882},"actual":"cat","predicted":"cat","url":"file:\/\/\/Users\/devopsthinh\/Downloads\/CH06code\/datasets\/dogs-vs-cats\/test\/cat\/cat.157.jpg"},{"predictions":{"dog":0.00017394189490005374,"cat":0.99982607364654541},"actual":"cat","predicted":"cat","url":"file:\/\/\/Users\/devopsthinh\/Downloads\/CH06code\/datasets\/dogs-vs-cats\/test\/cat\/cat.156.jpg"},{"predictions":{"dog":0.0026917310897260904,"cat":0.99730825424194336},"actual":"cat","predicted":"cat","url":"file:\/\/\/Users\/devopsthinh\/Downloads\/CH06code\/datasets\/dogs-vs-cats\/test\/cat\/cat.142.jpg"},{"predictions":{"cat":0.99917078018188477,"dog":0.00082919577835127711},"actual":"cat","predicted":"cat","url":"file:\/\/\/Users\/devopsthinh\/Downloads\/CH06code\/datasets\/dogs-vs-cats\/test\/cat\/cat.195.jpg"},{"predictions":{"dog":0.00096110848244279623,"cat":0.99903887510299683},"actual":"cat","predicted":"cat","url":"file:\/\/\/Users\/devopsthinh\/Downloads\/CH06code\/datasets\/dogs-vs-cats\/test\/cat\/cat.181.jpg"}]],"dog":[{"falsePositive":{}},[{"predictions":{"cat":0.45210838317871094,"dog":0.54789161682128906},"actual":"cat","predicted":"dog","url":"file:\/\/\/Users\/devopsthinh\/Downloads\/CH06code\/datasets\/dogs-vs-cats\/test\/cat\/cat.171.jpg"},{"predictions":{"cat":0.14480018615722656,"dog":0.85519981384277344},"actual":"cat","predicted":"dog","url":"file:\/\/\/Users\/devopsthinh\/Downloads\/CH06code\/datasets\/dogs-vs-cats\/test\/cat\/cat.146.jpg"}],{"truePositive":{}},[{"predictions":{"cat":0.00010164303967030719,"dog":0.99989837408065796},"actual":"dog","predicted":"dog","url":"file:\/\/\/Users\/devopsthinh\/Downloads\/CH06code\/datasets\/dogs-vs-cats\/test\/dog\/dog.167.jpg"},{"predictions":{"cat":0.44473129510879517,"dog":0.55526870489120483},"actual":"dog","predicted":"dog","url":"file:\/\/\/Users\/devopsthinh\/Downloads\/CH06code\/datasets\/dogs-vs-cats\/test\/dog\/dog.173.jpg"},{"predictions":{"dog":0.99960356950759888,"cat":0.0003964441129937768},"actual":"dog","predicted":"dog","url":"file:\/\/\/Users\/devopsthinh\/Downloads\/CH06code\/datasets\/dogs-vs-cats\/test\/dog\/dog.198.jpg"},{"predictions":{"cat":0.019818859174847603,"dog":0.98018115758895874},"actual":"dog","predicted":"dog","url":"file:\/\/\/Users\/devopsthinh\/Downloads\/CH06code\/datasets\/dogs-vs-cats\/test\/dog\/dog.199.jpg"},{"predictions":{"cat":0.29722744226455688,"dog":0.70277255773544312},"actual":"dog","predicted":"dog","url":"file:\/\/\/Users\/devopsthinh\/Downloads\/CH06code\/datasets\/dogs-vs-cats\/test\/dog\/dog.172.jpg"},{"predictions":{"cat":0.020601402968168259,"dog":0.97939860820770264},"actual":"dog","predicted":"dog","url":"file:\/\/\/Users\/devopsthinh\/Downloads\/CH06code\/datasets\/dogs-vs-cats\/test\/dog\/dog.166.jpg"},{"predictions":{"cat":0.0011739869369193912,"dog":0.99882602691650391},"actual":"dog","predicted":"dog","url":"file:\/\/\/Users\/devopsthinh\/Downloads\/CH06code\/datasets\/dogs-vs-cats\/test\/dog\/dog.170.jpg"},{"predictions":{"cat":0.069342218339443207,"dog":0.93065780401229858},"actual":"dog","predicted":"dog","url":"file:\/\/\/Users\/devopsthinh\/Downloads\/CH06code\/datasets\/dogs-vs-cats\/test\/dog\/dog.164.jpg"},{"predictions":{"dog":0.99547648429870605,"cat":0.0045235310681164265},"actual":"dog","predicted":"dog","url":"file:\/\/\/Users\/devopsthinh\/Downloads\/CH06code\/datasets\/dogs-vs-cats\/test\/dog\/dog.158.jpg"},{"predictions":{"cat":0.12397364526987076,"dog":0.87602633237838745},"actual":"dog","predicted":"dog","url":"file:\/\/\/Users\/devopsthinh\/Downloads\/CH06code\/datasets\/dogs-vs-cats\/test\/dog\/dog.159.jpg"},{"predictions":{"cat":0.014192442409694195,"dog":0.98580753803253174},"actual":"dog","predicted":"dog","url":"file:\/\/\/Users\/devopsthinh\/Downloads\/CH06code\/datasets\/dogs-vs-cats\/test\/dog\/dog.165.jpg"},{"predictions":{"dog":0.9943314790725708,"cat":0.005668549332767725},"actual":"dog","predicted":"dog","url":"file:\/\/\/Users\/devopsthinh\/Downloads\/CH06code\/datasets\/dogs-vs-cats\/test\/dog\/dog.171.jpg"},{"predictions":{"dog":0.98517125844955444,"cat":0.014828718267381191},"actual":"dog","predicted":"dog","url":"file:\/\/\/Users\/devopsthinh\/Downloads\/CH06code\/datasets\/dogs-vs-cats\/test\/dog\/dog.149.jpg"},{"predictions":{"cat":0.025693802163004875,"dog":0.97430622577667236},"actual":"dog","predicted":"dog","url":"file:\/\/\/Users\/devopsthinh\/Downloads\/CH06code\/datasets\/dogs-vs-cats\/test\/dog\/dog.175.jpg"},{"predictions":{"cat":0.00070005556335672736,"dog":0.99929994344711304},"actual":"dog","predicted":"dog","url":"file:\/\/\/Users\/devopsthinh\/Downloads\/CH06code\/datasets\/dogs-vs-cats\/test\/dog\/dog.161.jpg"},{"predictions":{"dog":0.99827611446380615,"cat":0.001723879249766469},"actual":"dog","predicted":"dog","url":"file:\/\/\/Users\/devopsthinh\/Downloads\/CH06code\/datasets\/dogs-vs-cats\/test\/dog\/dog.160.jpg"},{"predictions":{"dog":0.99610280990600586,"cat":0.0038972124457359314},"actual":"dog","predicted":"dog","url":"file:\/\/\/Users\/devopsthinh\/Downloads\/CH06code\/datasets\/dogs-vs-cats\/test\/dog\/dog.174.jpg"},{"predictions":{"cat":0.00072610873030498624,"dog":0.99927389621734619},"actual":"dog","predicted":"dog","url":"file:\/\/\/Users\/devopsthinh\/Downloads\/CH06code\/datasets\/dogs-vs-cats\/test\/dog\/dog.148.jpg"},{"predictions":{"dog":0.99275010824203491,"cat":0.0072498996742069721},"actual":"dog","predicted":"dog","url":"file:\/\/\/Users\/devopsthinh\/Downloads\/CH06code\/datasets\/dogs-vs-cats\/test\/dog\/dog.200.jpg"},{"predictions":{"dog":0.9884345531463623,"cat":0.011565469205379486},"actual":"dog","predicted":"dog","url":"file:\/\/\/Users\/devopsthinh\/Downloads\/CH06code\/datasets\/dogs-vs-cats\/test\/dog\/dog.162.jpg"},{"predictions":{"cat":0.041820421814918518,"dog":0.95817959308624268},"actual":"dog","predicted":"dog","url":"file:\/\/\/Users\/devopsthinh\/Downloads\/CH06code\/datasets\/dogs-vs-cats\/test\/dog\/dog.176.jpg"},{"predictions":{"dog":0.85439282655715942,"cat":0.14560718834400177},"actual":"dog","predicted":"dog","url":"file:\/\/\/Users\/devopsthinh\/Downloads\/CH06code\/datasets\/dogs-vs-cats\/test\/dog\/dog.189.jpg"},{"predictions":{"dog":0.97553986310958862,"cat":0.024460157379508018},"actual":"dog","predicted":"dog","url":"file:\/\/\/Users\/devopsthinh\/Downloads\/CH06code\/datasets\/dogs-vs-cats\/test\/dog\/dog.188.jpg"},{"predictions":{"dog":0.99934428930282593,"cat":0.0006557315937243402},"actual":"dog","predicted":"dog","url":"file:\/\/\/Users\/devopsthinh\/Downloads\/CH06code\/datasets\/dogs-vs-cats\/test\/dog\/dog.177.jpg"},{"predictions":{"dog":0.96687996387481689,"cat":0.033120062202215195},"actual":"dog","predicted":"dog","url":"file:\/\/\/Users\/devopsthinh\/Downloads\/CH06code\/datasets\/dogs-vs-cats\/test\/dog\/dog.163.jpg"},{"predictions":{"cat":0.013443190604448318,"dog":0.98655682802200317},"actual":"dog","predicted":"dog","url":"file:\/\/\/Users\/devopsthinh\/Downloads\/CH06code\/datasets\/dogs-vs-cats\/test\/dog\/dog.201.jpg"},{"predictions":{"cat":0.0043781213462352753,"dog":0.99562186002731323},"actual":"dog","predicted":"dog","url":"file:\/\/\/Users\/devopsthinh\/Downloads\/CH06code\/datasets\/dogs-vs-cats\/test\/dog\/dog.104.jpg"},{"predictions":{"dog":0.99212652444839478,"cat":0.00787346251308918},"actual":"dog","predicted":"dog","url":"file:\/\/\/Users\/devopsthinh\/Downloads\/CH06code\/datasets\/dogs-vs-cats\/test\/dog\/dog.110.jpg"},{"predictions":{"cat":0.0038065649569034576,"dog":0.99619340896606445},"actual":"dog","predicted":"dog","url":"file:\/\/\/Users\/devopsthinh\/Downloads\/CH06code\/datasets\/dogs-vs-cats\/test\/dog\/dog.138.jpg"},{"predictions":{"dog":0.99899810552597046,"cat":0.0010019061155617237},"actual":"dog","predicted":"dog","url":"file:\/\/\/Users\/devopsthinh\/Downloads\/CH06code\/datasets\/dogs-vs-cats\/test\/dog\/dog.139.jpg"},{"predictions":{"dog":0.95986121892929077,"cat":0.04013877734541893},"actual":"dog","predicted":"dog","url":"file:\/\/\/Users\/devopsthinh\/Downloads\/CH06code\/datasets\/dogs-vs-cats\/test\/dog\/dog.111.jpg"},{"predictions":{"cat":0.0050738328136503696,"dog":0.99492615461349487},"actual":"dog","predicted":"dog","url":"file:\/\/\/Users\/devopsthinh\/Downloads\/CH06code\/datasets\/dogs-vs-cats\/test\/dog\/dog.105.jpg"},{"predictions":{"dog":0.99094289541244507,"cat":0.0090571092441678047},"actual":"dog","predicted":"dog","url":"file:\/\/\/Users\/devopsthinh\/Downloads\/CH06code\/datasets\/dogs-vs-cats\/test\/dog\/dog.113.jpg"},{"predictions":{"cat":0.0065335235558450222,"dog":0.99346649646759033},"actual":"dog","predicted":"dog","url":"file:\/\/\/Users\/devopsthinh\/Downloads\/CH06code\/datasets\/dogs-vs-cats\/test\/dog\/dog.107.jpg"},{"predictions":{"dog":0.99255937337875366,"cat":0.0074406205676496029},"actual":"dog","predicted":"dog","url":"file:\/\/\/Users\/devopsthinh\/Downloads\/CH06code\/datasets\/dogs-vs-cats\/test\/dog\/dog.106.jpg"},{"predictions":{"cat":0.005891711451113224,"dog":0.99410825967788696},"actual":"dog","predicted":"dog","url":"file:\/\/\/Users\/devopsthinh\/Downloads\/CH06code\/datasets\/dogs-vs-cats\/test\/dog\/dog.112.jpg"},{"predictions":{"dog":0.99999368190765381,"cat":6.2988210629555397e-06},"actual":"dog","predicted":"dog","url":"file:\/\/\/Users\/devopsthinh\/Downloads\/CH06code\/datasets\/dogs-vs-cats\/test\/dog\/dog.116.jpg"},{"predictions":{"cat":0.00049579498590901494,"dog":0.9995042085647583},"actual":"dog","predicted":"dog","url":"file:\/\/\/Users\/devopsthinh\/Downloads\/CH06code\/datasets\/dogs-vs-cats\/test\/dog\/dog.102.jpg"},{"predictions":{"cat":4.768896906170994e-05,"dog":0.99995231628417969},"actual":"dog","predicted":"dog","url":"file:\/\/\/Users\/devopsthinh\/Downloads\/CH06code\/datasets\/dogs-vs-cats\/test\/dog\/dog.103.jpg"},{"predictions":{"cat":0.00055972975678741932,"dog":0.99944025278091431},"actual":"dog","predicted":"dog","url":"file:\/\/\/Users\/devopsthinh\/Downloads\/CH06code\/datasets\/dogs-vs-cats\/test\/dog\/dog.117.jpg"},{"predictions":{"dog":0.9551425576210022,"cat":0.044857412576675415},"actual":"dog","predicted":"dog","url":"file:\/\/\/Users\/devopsthinh\/Downloads\/CH06code\/datasets\/dogs-vs-cats\/test\/dog\/dog.129.jpg"},{"predictions":{"dog":0.9681246280670166,"cat":0.031875342130661011},"actual":"dog","predicted":"dog","url":"file:\/\/\/Users\/devopsthinh\/Downloads\/CH06code\/datasets\/dogs-vs-cats\/test\/dog\/dog.101.jpg"},{"predictions":{"cat":0.0044696689583361149,"dog":0.99553030729293823},"actual":"dog","predicted":"dog","url":"file:\/\/\/Users\/devopsthinh\/Downloads\/CH06code\/datasets\/dogs-vs-cats\/test\/dog\/dog.115.jpg"},{"predictions":{"cat":0.00025689462199807167,"dog":0.99974310398101807},"actual":"dog","predicted":"dog","url":"file:\/\/\/Users\/devopsthinh\/Downloads\/CH06code\/datasets\/dogs-vs-cats\/test\/dog\/dog.114.jpg"},{"predictions":{"dog":0.99857699871063232,"cat":0.0014230123488232493},"actual":"dog","predicted":"dog","url":"file:\/\/\/Users\/devopsthinh\/Downloads\/CH06code\/datasets\/dogs-vs-cats\/test\/dog\/dog.128.jpg"},{"predictions":{"dog":0.99470067024230957,"cat":0.0052993339486420155},"actual":"dog","predicted":"dog","url":"file:\/\/\/Users\/devopsthinh\/Downloads\/CH06code\/datasets\/dogs-vs-cats\/test\/dog\/dog.125.jpg"},{"predictions":{"cat":1.5610334230586886e-05,"dog":0.99998438358306885},"actual":"dog","predicted":"dog","url":"file:\/\/\/Users\/devopsthinh\/Downloads\/CH06code\/datasets\/dogs-vs-cats\/test\/dog\/dog.131.jpg"},{"predictions":{"cat":0.001895334804430604,"dog":0.99810469150543213},"actual":"dog","predicted":"dog","url":"file:\/\/\/Users\/devopsthinh\/Downloads\/CH06code\/datasets\/dogs-vs-cats\/test\/dog\/dog.119.jpg"},{"predictions":{"dog":0.99980634450912476,"cat":0.00019363536557648331},"actual":"dog","predicted":"dog","url":"file:\/\/\/Users\/devopsthinh\/Downloads\/CH06code\/datasets\/dogs-vs-cats\/test\/dog\/dog.118.jpg"},{"predictions":{"dog":0.91536432504653931,"cat":0.08463568240404129},"actual":"dog","predicted":"dog","url":"file:\/\/\/Users\/devopsthinh\/Downloads\/CH06code\/datasets\/dogs-vs-cats\/test\/dog\/dog.130.jpg"},{"predictions":{"dog":0.99396365880966187,"cat":0.0060363267548382282},"actual":"dog","predicted":"dog","url":"file:\/\/\/Users\/devopsthinh\/Downloads\/CH06code\/datasets\/dogs-vs-cats\/test\/dog\/dog.124.jpg"},{"predictions":{"cat":0.045263845473527908,"dog":0.95473617315292358},"actual":"dog","predicted":"dog","url":"file:\/\/\/Users\/devopsthinh\/Downloads\/CH06code\/datasets\/dogs-vs-cats\/test\/dog\/dog.132.jpg"},{"predictions":{"cat":0.023616481572389603,"dog":0.9763835072517395},"actual":"dog","predicted":"dog","url":"file:\/\/\/Users\/devopsthinh\/Downloads\/CH06code\/datasets\/dogs-vs-cats\/test\/dog\/dog.126.jpg"},{"predictions":{"dog":0.99894684553146362,"cat":0.0010531306033954024},"actual":"dog","predicted":"dog","url":"file:\/\/\/Users\/devopsthinh\/Downloads\/CH06code\/datasets\/dogs-vs-cats\/test\/dog\/dog.127.jpg"},{"predictions":{"dog":0.998801589012146,"cat":0.0011984375305473804},"actual":"dog","predicted":"dog","url":"file:\/\/\/Users\/devopsthinh\/Downloads\/CH06code\/datasets\/dogs-vs-cats\/test\/dog\/dog.133.jpg"},{"predictions":{"cat":0.013651726767420769,"dog":0.98634827136993408},"actual":"dog","predicted":"dog","url":"file:\/\/\/Users\/devopsthinh\/Downloads\/CH06code\/datasets\/dogs-vs-cats\/test\/dog\/dog.137.jpg"},{"predictions":{"dog":0.99978423118591309,"cat":0.00021578105224762112},"actual":"dog","predicted":"dog","url":"file:\/\/\/Users\/devopsthinh\/Downloads\/CH06code\/datasets\/dogs-vs-cats\/test\/dog\/dog.123.jpg"},{"predictions":{"dog":0.8720284104347229,"cat":0.12797157466411591},"actual":"dog","predicted":"dog","url":"file:\/\/\/Users\/devopsthinh\/Downloads\/CH06code\/datasets\/dogs-vs-cats\/test\/dog\/dog.122.jpg"},{"predictions":{"cat":0.00022566111874766648,"dog":0.99977433681488037},"actual":"dog","predicted":"dog","url":"file:\/\/\/Users\/devopsthinh\/Downloads\/CH06code\/datasets\/dogs-vs-cats\/test\/dog\/dog.136.jpg"},{"predictions":{"cat":0.0049500581808388233,"dog":0.99504995346069336},"actual":"dog","predicted":"dog","url":"file:\/\/\/Users\/devopsthinh\/Downloads\/CH06code\/datasets\/dogs-vs-cats\/test\/dog\/dog.108.jpg"},{"predictions":{"cat":0.045652884989976883,"dog":0.95434713363647461},"actual":"dog","predicted":"dog","url":"file:\/\/\/Users\/devopsthinh\/Downloads\/CH06code\/datasets\/dogs-vs-cats\/test\/dog\/dog.120.jpg"},{"predictions":{"cat":0.001144451554864645,"dog":0.99885553121566772},"actual":"dog","predicted":"dog","url":"file:\/\/\/Users\/devopsthinh\/Downloads\/CH06code\/datasets\/dogs-vs-cats\/test\/dog\/dog.134.jpg"},{"predictions":{"cat":0.015514090657234192,"dog":0.984485924243927},"actual":"dog","predicted":"dog","url":"file:\/\/\/Users\/devopsthinh\/Downloads\/CH06code\/datasets\/dogs-vs-cats\/test\/dog\/dog.135.jpg"},{"predictions":{"dog":0.99819666147232056,"cat":0.0018033175729215145},"actual":"dog","predicted":"dog","url":"file:\/\/\/Users\/devopsthinh\/Downloads\/CH06code\/datasets\/dogs-vs-cats\/test\/dog\/dog.121.jpg"},{"predictions":{"cat":0.0016750794602558017,"dog":0.9983249306678772},"actual":"dog","predicted":"dog","url":"file:\/\/\/Users\/devopsthinh\/Downloads\/CH06code\/datasets\/dogs-vs-cats\/test\/dog\/dog.109.jpg"},{"predictions":{"dog":0.99996870756149292,"cat":3.1270563340513036e-05},"actual":"dog","predicted":"dog","url":"file:\/\/\/Users\/devopsthinh\/Downloads\/CH06code\/datasets\/dogs-vs-cats\/test\/dog\/dog.146.jpg"},{"predictions":{"dog":0.80426472425460815,"cat":0.19573527574539185},"actual":"dog","predicted":"dog","url":"file:\/\/\/Users\/devopsthinh\/Downloads\/CH06code\/datasets\/dogs-vs-cats\/test\/dog\/dog.152.jpg"},{"predictions":{"cat":0.0076940371654927731,"dog":0.9923059344291687},"actual":"dog","predicted":"dog","url":"file:\/\/\/Users\/devopsthinh\/Downloads\/CH06code\/datasets\/dogs-vs-cats\/test\/dog\/dog.185.jpg"},{"predictions":{"dog":0.99976146221160889,"cat":0.00023855555627960712},"actual":"dog","predicted":"dog","url":"file:\/\/\/Users\/devopsthinh\/Downloads\/CH06code\/datasets\/dogs-vs-cats\/test\/dog\/dog.191.jpg"},{"predictions":{"cat":0.0013883034698665142,"dog":0.9986116886138916},"actual":"dog","predicted":"dog","url":"file:\/\/\/Users\/devopsthinh\/Downloads\/CH06code\/datasets\/dogs-vs-cats\/test\/dog\/dog.190.jpg"},{"predictions":{"cat":0.00046046997886151075,"dog":0.99953955411911011},"actual":"dog","predicted":"dog","url":"file:\/\/\/Users\/devopsthinh\/Downloads\/CH06code\/datasets\/dogs-vs-cats\/test\/dog\/dog.184.jpg"},{"predictions":{"cat":0.0028458167798817158,"dog":0.99715417623519897},"actual":"dog","predicted":"dog","url":"file:\/\/\/Users\/devopsthinh\/Downloads\/CH06code\/datasets\/dogs-vs-cats\/test\/dog\/dog.153.jpg"},{"predictions":{"cat":0.003794174175709486,"dog":0.99620580673217773},"actual":"dog","predicted":"dog","url":"file:\/\/\/Users\/devopsthinh\/Downloads\/CH06code\/datasets\/dogs-vs-cats\/test\/dog\/dog.147.jpg"},{"predictions":{"cat":0.0021961652673780918,"dog":0.99780380725860596},"actual":"dog","predicted":"dog","url":"file:\/\/\/Users\/devopsthinh\/Downloads\/CH06code\/datasets\/dogs-vs-cats\/test\/dog\/dog.151.jpg"},{"predictions":{"dog":0.99974209070205688,"cat":0.00025790880317799747},"actual":"dog","predicted":"dog","url":"file:\/\/\/Users\/devopsthinh\/Downloads\/CH06code\/datasets\/dogs-vs-cats\/test\/dog\/dog.145.jpg"},{"predictions":{"dog":0.97813314199447632,"cat":0.021866846829652786},"actual":"dog","predicted":"dog","url":"file:\/\/\/Users\/devopsthinh\/Downloads\/CH06code\/datasets\/dogs-vs-cats\/test\/dog\/dog.179.jpg"},{"predictions":{"cat":0.0012212040601298213,"dog":0.9987788200378418},"actual":"dog","predicted":"dog","url":"file:\/\/\/Users\/devopsthinh\/Downloads\/CH06code\/datasets\/dogs-vs-cats\/test\/dog\/dog.192.jpg"},{"predictions":{"dog":0.86109697818756104,"cat":0.13890302181243896},"actual":"dog","predicted":"dog","url":"file:\/\/\/Users\/devopsthinh\/Downloads\/CH06code\/datasets\/dogs-vs-cats\/test\/dog\/dog.186.jpg"},{"predictions":{"cat":0.01620030589401722,"dog":0.98379969596862793},"actual":"dog","predicted":"dog","url":"file:\/\/\/Users\/devopsthinh\/Downloads\/CH06code\/datasets\/dogs-vs-cats\/test\/dog\/dog.187.jpg"},{"predictions":{"cat":0.35327228903770447,"dog":0.64672768115997314},"actual":"dog","predicted":"dog","url":"file:\/\/\/Users\/devopsthinh\/Downloads\/CH06code\/datasets\/dogs-vs-cats\/test\/dog\/dog.193.jpg"},{"predictions":{"cat":0.0032951165921986103,"dog":0.99670487642288208},"actual":"dog","predicted":"dog","url":"file:\/\/\/Users\/devopsthinh\/Downloads\/CH06code\/datasets\/dogs-vs-cats\/test\/dog\/dog.178.jpg"},{"predictions":{"dog":0.99896609783172607,"cat":0.0010339196305721998},"actual":"dog","predicted":"dog","url":"file:\/\/\/Users\/devopsthinh\/Downloads\/CH06code\/datasets\/dogs-vs-cats\/test\/dog\/dog.144.jpg"},{"predictions":{"cat":0.023516444489359856,"dog":0.97648358345031738},"actual":"dog","predicted":"dog","url":"file:\/\/\/Users\/devopsthinh\/Downloads\/CH06code\/datasets\/dogs-vs-cats\/test\/dog\/dog.150.jpg"},{"predictions":{"dog":0.99354952573776245,"cat":0.0064504994079470634},"actual":"dog","predicted":"dog","url":"file:\/\/\/Users\/devopsthinh\/Downloads\/CH06code\/datasets\/dogs-vs-cats\/test\/dog\/dog.168.jpg"},{"predictions":{"dog":0.85167354345321655,"cat":0.14832648634910583},"actual":"dog","predicted":"dog","url":"file:\/\/\/Users\/devopsthinh\/Downloads\/CH06code\/datasets\/dogs-vs-cats\/test\/dog\/dog.154.jpg"},{"predictions":{"cat":0.0033110487274825573,"dog":0.99668896198272705},"actual":"dog","predicted":"dog","url":"file:\/\/\/Users\/devopsthinh\/Downloads\/CH06code\/datasets\/dogs-vs-cats\/test\/dog\/dog.140.jpg"},{"predictions":{"cat":0.00033160316525027156,"dog":0.9996684193611145},"actual":"dog","predicted":"dog","url":"file:\/\/\/Users\/devopsthinh\/Downloads\/CH06code\/datasets\/dogs-vs-cats\/test\/dog\/dog.197.jpg"},{"predictions":{"dog":0.99246186017990112,"cat":0.0075381407514214516},"actual":"dog","predicted":"dog","url":"file:\/\/\/Users\/devopsthinh\/Downloads\/CH06code\/datasets\/dogs-vs-cats\/test\/dog\/dog.183.jpg"},{"predictions":{"cat":0.0094393324106931686,"dog":0.99056065082550049},"actual":"dog","predicted":"dog","url":"file:\/\/\/Users\/devopsthinh\/Downloads\/CH06code\/datasets\/dogs-vs-cats\/test\/dog\/dog.182.jpg"},{"predictions":{"dog":0.9999576210975647,"cat":4.2376406781841069e-05},"actual":"dog","predicted":"dog","url":"file:\/\/\/Users\/devopsthinh\/Downloads\/CH06code\/datasets\/dogs-vs-cats\/test\/dog\/dog.196.jpg"},{"predictions":{"dog":0.99979484081268311,"cat":0.00020517651864793152},"actual":"dog","predicted":"dog","url":"file:\/\/\/Users\/devopsthinh\/Downloads\/CH06code\/datasets\/dogs-vs-cats\/test\/dog\/dog.141.jpg"},{"predictions":{"cat":0.04406009241938591,"dog":0.9559398889541626},"actual":"dog","predicted":"dog","url":"file:\/\/\/Users\/devopsthinh\/Downloads\/CH06code\/datasets\/dogs-vs-cats\/test\/dog\/dog.155.jpg"},{"predictions":{"dog":0.99731767177581787,"cat":0.0026823012158274651},"actual":"dog","predicted":"dog","url":"file:\/\/\/Users\/devopsthinh\/Downloads\/CH06code\/datasets\/dogs-vs-cats\/test\/dog\/dog.169.jpg"},{"predictions":{"dog":0.99932676553726196,"cat":0.0006732128094881773},"actual":"dog","predicted":"dog","url":"file:\/\/\/Users\/devopsthinh\/Downloads\/CH06code\/datasets\/dogs-vs-cats\/test\/dog\/dog.143.jpg"},{"predictions":{"dog":0.99983519315719604,"cat":0.00016482500359416008},"actual":"dog","predicted":"dog","url":"file:\/\/\/Users\/devopsthinh\/Downloads\/CH06code\/datasets\/dogs-vs-cats\/test\/dog\/dog.157.jpg"},{"predictions":{"dog":0.71632808446884155,"cat":0.28367194533348083},"actual":"dog","predicted":"dog","url":"file:\/\/\/Users\/devopsthinh\/Downloads\/CH06code\/datasets\/dogs-vs-cats\/test\/dog\/dog.180.jpg"},{"predictions":{"dog":0.99161499738693237,"cat":0.0083850082010030746},"actual":"dog","predicted":"dog","url":"file:\/\/\/Users\/devopsthinh\/Downloads\/CH06code\/datasets\/dogs-vs-cats\/test\/dog\/dog.194.jpg"},{"predictions":{"cat":0.00025839812587946653,"dog":0.99974161386489868},"actual":"dog","predicted":"dog","url":"file:\/\/\/Users\/devopsthinh\/Downloads\/CH06code\/datasets\/dogs-vs-cats\/test\/dog\/dog.195.jpg"},{"predictions":{"dog":0.89491963386535645,"cat":0.10508035123348236},"actual":"dog","predicted":"dog","url":"file:\/\/\/Users\/devopsthinh\/Downloads\/CH06code\/datasets\/dogs-vs-cats\/test\/dog\/dog.181.jpg"},{"predictions":{"cat":0.096912629902362823,"dog":0.90308737754821777},"actual":"dog","predicted":"dog","url":"file:\/\/\/Users\/devopsthinh\/Downloads\/CH06code\/datasets\/dogs-vs-cats\/test\/dog\/dog.156.jpg"},{"predictions":{"dog":0.96708279848098755,"cat":0.032917212694883347},"actual":"dog","predicted":"dog","url":"file:\/\/\/Users\/devopsthinh\/Downloads\/CH06code\/datasets\/dogs-vs-cats\/test\/dog\/dog.142.jpg"}],{"falseNegative":{}},[]]}},"accuracy":0.99009900990099009,"statsByLabel":{"cat":{"count":101,"precisionRecall":{"success":{"recall":0.98019801980198018,"precision":1}}},"dog":{"count":101,"precisionRecall":{"success":{"recall":1,"precision":0.98058252427184467}}}}}},"createdDate":"2023-04-25T11:05:57Z","id":"9ba4e60e-1f24-4964-8461-5023f8d31712","dataURL":"file:\/\/\/Users\/devopsthinh\/Downloads\/CH06code\/datasets\/dogs-vs-cats\/test\/","dataSourceID":"3DE97716-5C72-4114-B0C4-2278BBFE0BEE","dataResult":{"itemsCount":202,"createdDate":"2023-04-25T11:07:02Z","dataURL":"file:\/\/\/Users\/devopsthinh\/Downloads\/CH06code\/datasets\/dogs-vs-cats\/test\/","dataSourceID":"3DE97716-5C72-4114-B0C4-2278BBFE0BEE","classesCount":2,"dataAnalysis":{"summary":{"sampleCount":202,"classCount":2,"canUseValidation":1},"issues":[{"description":"2 classes found, including dog, cat","severity":"debug"},{"description":"202 images found, automatically creating validation set","severity":"good"},{"description":"Smallest class is \"cat\" with 101 images","severity":"debug"},{"description":"Largest class is \"dog\" with 101 images","severity":"debug"}],"classifierAnalysis":{"labelStats":{"cat":101,"dog":101}}}},"analysedDataType":"datasource","accuracy":0.99009900990099009,"startTime":"2023-04-25T11:07:04Z","finishTime":"2023-04-25T11:07:16Z"}]},"activityEntities":["trainingStarted",[{"id":"5F208B2A-EF89-42DB-B860-B9479B190CE8","title":"Training Started","createdDate":"2023-04-25T08:54:03Z","event":"trainingStarted","subtitle":"25 iterations"}],"experimentCreated",[{"id":"DD4EDDC5-99EA-4D5A-90F0-8337C0D3D77F","title":"Model Source Created","createdDate":"2023-04-25T08:43:08Z","event":"experimentCreated","subtitle":"DogsCatsTransferLearningClassifier 1"}],"evaluationStarted",[{"id":"AE9042DF-C5D9-4DA8-A9C4-B33D62BC0548","title":"Testing Started","createdDate":"2023-04-25T11:07:04Z","event":"evaluationStarted","subtitle":"DogsCatsTransferLearningClassifier 1"}],"evaluationFinished",[{"id":"FA22BF58-29E8-4F5E-9280-60DAA7DC8E88","title":"Testing Completed","createdDate":"2023-04-25T11:07:16Z","event":"evaluationFinished","subtitle":"DogsCatsTransferLearningClassifier 1"}],"trainingFinished",[{"id":"7CFE4997-B118-4971-A6E9-05C234FDF60C","title":"Training Completed","createdDate":"2023-04-25T09:31:10Z","event":"trainingFinished","subtitle":"25 iterations"}],"trainingDataAdded",[{"id":"A825565D-3753-49DA-89BB-8849D905F341","title":"Training Data Added","createdDate":"2023-04-25T08:51:38Z","event":"trainingDataAdded","subtitle":"train"}]],"evaluationState":"evaluated","title":"DogsCatsTransferLearningClassifier 1","evaluationEntity":{"id":"f5e1b0bc-493c-4e08-8dac-f967c11e3ea6","analysedDataType":"none","dataResult":{}},"snapshotRole":{"withoutSnapshots":0},"contentDataResult":{"createdDate":"2023-04-25T08:43:08Z"},"modifiedDate":"2023-04-25T11:12:28Z","preferredFilename":"DogsCatsTransferLearningClassifier 1"}